otobo/__init__.py
otobo/mappers.py
otobo/py.typed
otobo/clients/__init__.py
otobo/clients/otobo_client.py
otobo/domain_models/__init__.py
otobo/domain_models/basic_auth_model.py
otobo/domain_models/otobo_client_config.py
otobo/domain_models/ticket_models.py
otobo/domain_models/ticket_operation.py
otobo/models/__init__.py
otobo/models/request_models.py
otobo/models/response_models.py
otobo/models/ticket_models.py
otobo/scripts/__init__.py
otobo/scripts/getting_started.py
otobo/scripts/setup_webservices.py
otobo/util/__init__.py
otobo/util/otobo_errors.py
otobo/util/webservice_config.py
otobo-4.1.7.dist-info/METADATA
otobo-4.1.7.dist-info/WHEEL
otobo-4.1.7.dist-info/top_level.txt
otobo-4.1.7.dist-info/RECORD
